{
  "name": "Trialeti Trophy 2025 (ISU CS)",
  "type": "CS",
  "city": "Тбилиси",
  "country": "Грузия",
  "start": "2025-10-08",
  "end": "2025-10-11",
  "participants": {
    "men": [
      "🇦🇿 Владимир Литвинцев",
      "🇷🇺 Георгий Рещенко",
      "🇪🇸 Пабло Гарсия",
      "🇪🇪 Арлет Леванди",
      "🇪🇪 Александр Селевко",
      "🇬🇪 Ника Эгадзе",
      "🇩🇪 Никита Старостин",
      "🇯🇵 Сота Ямамото",
      "🇷🇺 Никита Кривошеев",
      "🇰🇷 Сихён Ли",
      "🇨🇦 Даниэль Корабельник",
      "🇲🇽 Донован Каррильо",
      "🇷🇺 Владимир Самойлов",
      "🇸🇰 Адам Хагара",
      "🇺🇦 Кирилл Марсак",
      "🇺🇸 Джейсон Браун",
      "🇺🇸 Томоки Хиватаси",
      "🇺🇸 Даниэль Мартынов"
    ],
    "women": [
      "🇦🇿 Сабина Алиева",
      "🇦🇿 Наргиз Сулейманова",
      "🇷🇺 Стефания Яковлева",
      "🇨🇿 Элишка Бржезинова",
      "🇪🇪 Натали Лангербаур",
      "🇪🇪 Кристина Лисовская",
      "🇫🇮 Линнеа Седер",
      "🇫🇮 Иида Кархунен",
      "🇫🇮 Оливия Лиско",
      "🇬🇪 Анастасия Губанова",
      "🇩🇪 Сара Мари Пеш",
      "🇪🇪 Элизабет Гервиц",
      "🇺🇦 Мария Сенюк",
      "🇮🇹 Анна Пеццетта",
      "🇯🇵 Ринка Ватанабэ",
      "🇰🇿 Амина Алексеева",
      "🇷🇺 София Фарафонова",
      "🇷🇺 Русалина Шакрова",
      "🇰🇷 Соён Ким",
      "🇰🇷 Хэин Ли",
      "🇰🇷 Ахсун Юн",
      "🇰🇷 Хисю Хан",
      "🇱🇹 Меда Варякойте",
      "🇲🇽 Андреа Монтеcинос Канту",
      "🇺🇸 Старр Эндрюс",
      "🇺🇸 Ава Мари Зиглер"
    ],
    "pairs": [
      "🇷🇺 Карина Акопова / Никита Рахманин",
      "🇫🇷 Луиза Эрхард / Матис Пеллегрис",
      "🇬🇪 Анастасия Метелкина / Лука Берулава",
      "🇩🇪 Минерва Фабиен Хазе / Никита Володин",
      "🇩🇪 Летиция Рошер / Луис Шустер",
      "🇮🇹 Лукреция Беккари / Маттео Гуаризе",
      "🇳🇱 Дарья Данилова / Михел Циба",
      "🇨🇭 Юлия Щетинина / Михал Возняк",
      "🇨🇭 Оксана Вуйямо / Том Бувар",
      "🇺🇸 Эмили Чан / Спенсер Акира Хау",
      "🇺🇸 Элли Кам / Дэнни О’Ши",
      "🇸🇰 Рейган Мосс / Якуб Гальбави"
    ],
    "dance": [
      "🇮🇹 Кристина Добросердова / Алессандро Пеллегрини",
      "🇦🇺 Холли Харрис / Джейсон Чан",
      "🇩🇪 Саманта Риттер / Даниэль Брыкалов",
      "🇺🇦 Максин Везерби / Александр Колосовский",
      "🇧🇷 Наталия Палью-Невес / Джейн Панесар",
      "🇨🇾 Ангелина Кудрявцева / Илья Каранкевич",
      "🇫🇷 Лоисия Демужо / Тео Ле Мерсье",
      "🇫🇷 Селина Фраджи / Жан-Анс Фурно",
      "🇬🇧 Фиби Беккер / Джеймс Эрнандес",
      "🇷🇺 Диана Дэвис / Глеб Смолкин",
      "🇬🇪 Мария Казакова / Владислав Касинский",
      "🇩🇪 Карла Мария Карль / Кай Хоферихтер",
      "🇭🇺 Эмеше Чсишер / Марк Шапиро",
      "🇯🇵 Утана Ёсида / Масаё Морита",
      "🇺🇦 София Довгаль / Виктор Кулеша",
      "🇺🇸 Зои Ларсон / Андрей Капран"
    ]
  }
}
{
  "name": "Гран-при Франции 2025 (ISU)",
  "type": "GP",
  "city": "Анже",
  "country": "Франция",
  "start": "2025-10-17",
  "end": "2025-10-19",
  "participants": {
    "men": [
      "🇪🇪 Михаил Селевко",
      "🇫🇷 Люк Экономидес",
      "🇫🇷 Франсуа Пито",
      "🇫🇷 Адам Сяо Хим Фа",
      "🇬🇪 Ника Эгадзе",
      "🇮🇹 Габриэле Франджипани",
      "🇯🇵 Као Миура",
      "🇯🇵 Тацуя Цубои",
      "🇨🇭 Лукас Бритшги",
      "🇺🇸 Илья Малинин",
      "🇺🇸 Максим Наумов",
      "🇺🇸 Эндрю Торгашев"
    ],
    "women": [
      "🇪🇪 Ниина Петрокина",
      "🇫🇷 Клеманс Майинду",
      "🇫🇷 Лорин Шильд",
      "🇫🇷 Леа Серна",
      "🇯🇵 Ами Накаи",
      "🇯🇵 Каори Сакамото",
      "🇯🇵 Рион Сумийоси",
      "🇰🇷 Чхэён Ким",
      "🇰🇷 Ён Ю",
      "🇨🇭 Ливия Кайзер",
      "🇺🇸 Изабо Левито",
      "🇺🇸 Элис Лин-Грейси"
    ],
    "pairs": [
      "🇨🇦 Деанна Стеллато-Дудек / Максим Дешам",
      "🇫🇷 Орели Фаула / Тео Белль",
      "🇫🇷 Камиль Ковалёв / Павел Ковалёв",
      "🇫🇷 Меган Весенберг / Денис Стрекалин",
      "🇨🇭 Мария Павлова / Алексей Святченко",
      "🇯🇵 Рику Миура / Рюити Кихара",
      "🇺🇸 Кейти Макбис / Даниил Паркман",
      "🇺🇸 Одри Шин / Балаж Надь"
    ],
    "dance": [
      "🇫🇷 Мари-Жад Лорио / Ромен Ле Гак",
      "🇨🇦 Лоранс Фурнье-Бодри / Гийом Сизерон",
      "🇫🇷 Селина Фраджи / Жан-Анс Фурно",
      "🇫🇷 Наташа Лагуж / Арно Каффа",
      "🇬🇧 Лайла Фир / Льюис Гибсон",
      "🇷🇺 Диана Дэвис / Глеб Смолкин",
      "🇮🇹 Шарлен Гиньяр / Марко Фаббри",
      "🇱🇹 Эллисон Рид / Саулиус Амбрулевичюс",
      "🇺🇸 Эмили Братти / Иэн Сомервилл",
      "🇺🇸 Ева Пейт / Логан Бай"
    ]
  }
}
{
  "name": "Гран-при Китая 2025 (ISU)",
  "type": "GP",
  "city": "Чунцин",
  "country": "Китай",
  "start": "2025-10-31",
  "end": "2025-11-02",
  "participants": {
    "men": [
      "🇨🇦 Конрад Орзел",
      "🇨🇳 Цзиньюй Сюэ",
      "🇨🇳 Ю Дже",
      "🇨🇳 Чэнь Юньяо",
      "🇫🇷 Кевин Аймо",
      "🇩🇪 Пол Фенц",
      "🇯🇵 Юма Кагияма",
      "🇯🇵 Сёма Уно",
      "🇰🇷 Джунхван Ча",
      "🇺🇸 Камден Пулкинен",
      "🇺🇸 Илья Малинин",
      "🇺🇸 Даниэль Грейссел"
    ],
    "women": [
      "🇨🇦 Мэдди Скизас",
      "🇨🇳 Ань Чэнь",
      "🇨🇳 Чэнь Хунъи",
      "🇨🇳 Анни Чэнь",
      "🇫🇮 Янелле Лундин",
      "🇫🇷 Лорин Мэдлен Шильд",
      "🇯🇵 Михо Такахаси",
      "🇯🇵 Рион Сумийоси",
      "🇯🇵 Мао Симада",
      "🇰🇷 Чхэён Ким",
      "🇺🇸 Элис Лин-Грейси",
      "🇺🇸 Изабо Левито"
    ],
    "pairs": [
      "🇨🇳 Чэн Пэн / Ян Цзинь",
      "🇨🇳 Ван Лисян / Чжу Яньхань",
      "🇨🇳 Юй Цзяюй / Чэнь Хунъянь",
      "🇩🇪 Минерва Фабиен Хазе / Никита Володин",
      "🇮🇹 Ребекка Гилоди / Филиппо Амброзини",
      "🇯🇵 Рику Миура / Рюити Кихара",
      "🇰🇷 Хеён Джи / Джей Вон Сео",
      "🇺🇸 Кэти Макбис / Даниил Паркман",
      "🇺🇸 Эмили Чан / Спенсер Акира Хау"
    ],
    "dance": [
      "🇨🇳 Ван Шуэй / Лю Синью",
      "🇨🇳 Чжан Юэ / Хоу Синь",
      "🇨🇦 Пайпер Гиллес / Поль Пуарье",
      "🇫🇷 Мари-Жад Лорио / Ромен Ле Гак",
      "🇬🇧 Лайла Фир / Льюис Гибсон",
      "🇯🇵 Канон Такахаши / Сёто Накахара",
      "🇰🇷 Хан Юра / Лим Минью",
      "🇺🇸 Эмили Братти / Иэн Сомервилл",
      "🇺🇸 Каролина Грин / Майкл Парсонс"
    ]
  }
}
{
  "name": "Гран-при Канады 2025 (ISU)",
  "type": "GP",
  "city": "Калгари",
  "country": "Канада",
  "start": "2025-10-24",
  "end": "2025-10-26",
  "participants": {
    "men": [
      "🇨🇦 Стивен Гогоолев",
      "🇨🇦 Конрад Орзел",
      "🇨🇦 Уэсли Чу",
      "🇫🇷 Адам Сяо Хим Фа",
      "🇮🇹 Маттео Риццо",
      "🇯🇵 Сота Ямамото",
      "🇯🇵 Као Миура",
      "🇰🇷 Джунхван Ча",
      "🇨🇭 Лукас Бритшги",
      "🇺🇸 Илья Малинин"
    ],
    "women": [
      "🇨🇦 Мэдди Скизас",
      "🇫🇮 Янелле Лундин",
      "🇮🇹 Анна Пеццетта",
      "🇯🇵 Каори Сакамото",
      "🇯🇵 Рион Сумийоси",
      "🇰🇷 Чхэён Ким",
      "🇰🇷 Ён Ю",
      "🇺🇸 Изабо Левито",
      "🇺🇸 Ава Мари Зиглер"
    ],
    "pairs": [
      "🇨🇦 Деанна Стеллато-Дудек / Максим Дешам",
      "🇨🇦 Брук МакИнтош / Бенджамин Мимс",
      "🇩🇪 Минерва Фабиен Хазе / Никита Володин",
      "🇮🇹 Лукреция Беккари / Маттео Гуаризе",
      "🇯🇵 Рику Миура / Рюити Кихара",
      "🇺🇸 Элли Кам / Дэнни О’Ши",
      "🇺🇸 Кейти Макбис / Даниил Паркман"
    ],
    "dance": [
      "🇨🇦 Пайпер Гиллес / Поль Пуарье",
      "🇨🇦 Лоранс Фурнье-Бодри / Николас Соренсен",
      "🇮🇹 Шарлен Гиньяр / Марко Фаббри",
      "🇫🇷 Мари-Жад Лорио / Ромен Ле Гак",
      "🇯🇵 Канон Такахаши / Сёто Накахара",
      "🇺🇸 Каролина Грин / Майкл Парсонс",
      "🇺🇸 Ева Пейт / Логан Бай"
    ]
  }
}{
  "name": "Skate America 2025 (ISU)",
  "type": "GP",
  "city": "Лас-Вегас",
  "country": "США",
  "start": "2025-10-17",
  "end": "2025-10-19",
  "participants": {
    "men": [
      "🇺🇸 Илья Малинин",
      "🇺🇸 Камден Пулкинен",
      "🇺🇸 Эндрю Торгашев",
      "🇨🇦 Стивен Гогоолев",
      "🇨🇦 Конрад Орзел",
      "🇫🇷 Адам Сяо Хим Фа",
      "🇯🇵 Юма Кагияма",
      "🇰🇷 Джунхван Ча",
      "🇨🇭 Лукас Бритшги",
      "🇩🇪 Никита Старостин"
    ],
    "women": [
      "🇺🇸 Изабо Левито",
      "🇺🇸 Ава Мари Зиглер",
      "🇺🇸 Одри Шин",
      "🇨🇦 Мэдди Скизас",
      "🇫🇷 Леа Серна",
      "🇯🇵 Каори Сакамото",
      "🇰🇷 Чхэён Ким",
      "🇨🇭 Ливия Кайзер",
      "🇺🇦 Анастасия Губанова",
      "🇮🇹 Анна Пеццетта"
    ],
    "pairs": [
      "🇺🇸 Элли Кам / Дэнни О’Ши",
      "🇺🇸 Кейти Макбис / Даниил Паркман",
      "🇺🇸 Эмили Чан / Спенсер Акира Хау",
      "🇨🇦 Деанна Стеллато-Дудек / Максим Дешам",
      "🇩🇪 Минерва Фабиен Хазе / Никита Володин",
      "🇮🇹 Лукреция Беккари / Маттео Гуаризе",
      "🇯🇵 Рику Миура / Рюити Кихара"
    ],
    "dance": [
      "🇺🇸 Каролина Грин / Майкл Парсонс",
      "🇺🇸 Ева Пейт / Логан Бай",
      "🇺🇸 Эмили Братти / Иэн Сомервилл",
      "🇨🇦 Пайпер Гиллес / Поль Пуарье",
      "🇮🇹 Шарлен Гиньяр / Марко Фаббри",
      "🇫🇷 Мари-Жад Лорио / Ромен Ле Гак",
      "🇯🇵 Канон Такахаши / Сёто Накахара"
    ]
  }
}

{
  "name": "NHK Trophy 2025 (ISU)",
  "type": "GP",
  "city": "Осака",
  "country": "Япония",
  "start": "2025-11-07",
  "end": "2025-11-09",
  "participants": {
    "men": [
      "🇯🇵 Юма Кагияма",
      "🇯🇵 Сота Ямамото",
      "🇯🇵 Тацуя Цубои",
      "🇨🇦 Стивен Гогоолев",
      "🇫🇷 Адам Сяо Хим Фа",
      "🇮🇹 Маттео Риццо",
      "🇺🇸 Илья Малинин",
      "🇺🇸 Камден Пулкинен",
      "🇨🇭 Лукас Бритшги",
      "🇰🇷 Джунхван Ча"
    ],
    "women": [
      "🇯🇵 Каори Сакамото",
      "🇯🇵 Мао Симада",
      "🇯🇵 Рион Сумийоси",
      "🇯🇵 Михо Такахаси",
      "🇨🇦 Мэдди Скизас",
      "🇫🇮 Янелле Лундин",
      "🇰🇷 Чхэён Ким",
      "🇺🇸 Изабо Левито",
      "🇺🇸 Ава Мари Зиглер",
      "🇮🇹 Анна Пеццетта"
    ],
    "pairs": [
      "🇯🇵 Рику Миура / Рюити Кихара",
      "🇩🇪 Минерва Фабиен Хазе / Никита Володин",
      "🇮🇹 Лукреция Беккари / Маттео Гуаризе",
      "🇨🇦 Деанна Стеллато-Дудек / Максим Дешам",
      "🇺🇸 Элли Кам / Дэнни О’Ши",
      "🇺🇸 Кейти Макбис / Даниил Паркман"
    ],
    "dance": [
      "🇯🇵 Канон Такахаши / Сёто Накахара",
      "🇨🇦 Пайпер Гиллес / Поль Пуарье",
      "🇮🇹 Шарлен Гиньяр / Марко Фаббри",
      "🇫🇷 Мари-Жад Лорио / Ромен Ле Гак",
      "🇺🇸 Каролина Грин / Майкл Парсонс",
      "🇺🇸 Ева Пейт / Логан Бай",
      "🇰🇷 Хан Юра / Лим Минью"
    ]
  }
}
